distance.py
statistical_distance-0.9.1.dist-info/LICENSE
statistical_distance-0.9.1.dist-info/WHEEL
statistical_distance-0.9.1.dist-info/METADATA
statistical_distance-0.9.1.dist-info/RECORD
