Metadata-Version: 2.1
Name: statistical-distance
Version: 0.9.1
Summary: Distance measures to compare two probability density functions.
Keywords: distance,statistics,measure,metric
Author-email: Andrzej Zielezinski <a.zielezinski@gmail.com>
Requires-Python: >=3.6
Classifier: License :: OSI Approved :: GNU General Public License v3 or later (GPLv3+)
Classifier: Programming Language :: Python
Classifier: Programming Language :: Python :: 3
Classifier: Operating System :: OS Independent
Classifier: Topic :: Scientific/Engineering
Classifier: Topic :: Scientific/Engineering :: Mathematics
Requires-Dist: numpy >=1.16.4
Project-URL: Documentation, https://github.com/aziele/statistical-distance
Project-URL: Source, https://github.com/aziele/statistical-distance
